README.rst
setup.py
sphinxcontrib/__init__.py
sphinxcontrib/showterm.py
sphinxcontrib_showterm.egg-info/PKG-INFO
sphinxcontrib_showterm.egg-info/SOURCES.txt
sphinxcontrib_showterm.egg-info/dependency_links.txt
sphinxcontrib_showterm.egg-info/namespace_packages.txt
sphinxcontrib_showterm.egg-info/not-zip-safe
sphinxcontrib_showterm.egg-info/requires.txt
sphinxcontrib_showterm.egg-info/top_level.txt
tests/__init__.py
tests/test_argparse_type.py
tests/test_basic_math.py
tests/test_best_prefix_BASE.py
tests/test_best_prefix_NIST.py
tests/test_best_prefix_SI.py
tests/test_bitwise_operations.py
tests/test_cli.py
tests/test_context_manager.py
tests/test_file_size.py
tests/test_future_math.py
tests/test_init.py
tests/test_instantiating.py
tests/test_parse.py
tests/test_progressbar.py
tests/test_properties.py
tests/test_query_device_capacity.py
tests/test_representation.py
tests/test_rich_comparison.py
tests/test_sorting.py
tests/test_to_Type_conversion.py
tests/test_to_built_in_conversion.py